module/__init__.py
module/capacity_status.py
module/operation.py
pruebajorgemarmol-0.1.dist-info/METADATA
pruebajorgemarmol-0.1.dist-info/WHEEL
pruebajorgemarmol-0.1.dist-info/top_level.txt
pruebajorgemarmol-0.1.dist-info/RECORD
