Metadata-Version: 2.1
Name: pruebajorgemarmol
Version: 0.1
Requires-Dist: azure-identity
Requires-Dist: azure-mgmt-resource
